_pyblemesh.cp35-win32.pyd
pyblemesh-0.1.dist-info/DESCRIPTION.rst
pyblemesh-0.1.dist-info/METADATA
pyblemesh-0.1.dist-info/RECORD
pyblemesh-0.1.dist-info/WHEEL
pyblemesh-0.1.dist-info/metadata.json
pyblemesh-0.1.dist-info/top_level.txt
