Metadata-Version: 2.0
Name: pyblemesh
Version: 0.1
Summary: Python module for Bluetooth Low Energy mesh specification.
Home-page: UNKNOWN
Author: zuolongjun
Author-email: UNKNOWN
License: UNKNOWN
Platform: UNKNOWN
